dataops_llm/__init__.py
dataops_llm/api.py
dataops_llm/config.py
dataops_llm/exceptions.py
dataops_llm/engine/__init__.py
dataops_llm/engine/codegen.py
dataops_llm/engine/executor.py
dataops_llm/engine/interpreter.py
dataops_llm/engine/planner.py
dataops_llm/engine/validator.py
dataops_llm/llm/__init__.py
dataops_llm/llm/client.py
dataops_llm/llm/json_utils.py
dataops_llm/llm/prompts.py
dataops_llm/llm/schemas.py
dataops_llm/models/__init__.py
dataops_llm/models/intent.py
dataops_llm/models/plan.py
dataops_llm/models/result.py
dataops_llm/sandbox/__init__.py
dataops_llm/sandbox/context.py
dataops_llm/sandbox/limits.py
dataops_llm/sandbox/runtime.py
dataops_llm/utils/__init__.py
dataops_llm/utils/file_loader.py
dataops_llm/web/__init__.py
dataops_llm/web/app.py
dataops_llm/web/models.py
dataops_llm/web/routes.py
dataops_llm-0.1.0.dist-info/licenses/LICENSE
dataops_llm-0.1.0.dist-info/METADATA
dataops_llm-0.1.0.dist-info/WHEEL
dataops_llm-0.1.0.dist-info/top_level.txt
dataops_llm-0.1.0.dist-info/RECORD
