Metadata-Version: 2.4
Name: dataops-llm
Version: 0.1.0
Summary: LLM-powered data operations engine for Excel/CSV files
Author-email: Islam Abd-Elhady <eslamabdo71239@gmail.com>
License: MIT
Project-URL: Homepage, https://github.com/Islam-hady9/dataops-llm-engine
Project-URL: Documentation, https://github.com/Islam-hady9/dataops-llm-engine#readme
Project-URL: Repository, https://github.com/Islam-hady9/dataops-llm-engine
Project-URL: Bug Tracker, https://github.com/Islam-hady9/dataops-llm-engine/issues
Classifier: Development Status :: 3 - Alpha
Classifier: Intended Audience :: Developers
Classifier: License :: OSI Approved :: MIT License
Classifier: Programming Language :: Python :: 3
Classifier: Programming Language :: Python :: 3.10
Classifier: Programming Language :: Python :: 3.11
Classifier: Programming Language :: Python :: 3.12
Requires-Python: >=3.10
License-File: LICENSE
Requires-Dist: litellm>=1.0.0
Requires-Dist: pandas>=2.0.0
Requires-Dist: openpyxl>=3.1.0
Requires-Dist: pydantic>=2.0.0
Requires-Dist: pydantic-settings>=2.0.0
Requires-Dist: fastapi>=0.100.0
Requires-Dist: uvicorn>=0.23.0
Requires-Dist: psutil>=5.9.0
Requires-Dist: python-dotenv>=1.0.0
Provides-Extra: dev
Requires-Dist: pytest>=7.4.0; extra == "dev"
Requires-Dist: pytest-asyncio>=0.21.0; extra == "dev"
Requires-Dist: pytest-cov>=4.1.0; extra == "dev"
Requires-Dist: black>=23.0.0; extra == "dev"
Requires-Dist: ruff>=0.1.0; extra == "dev"
Requires-Dist: mypy>=1.5.0; extra == "dev"
Requires-Dist: types-psutil; extra == "dev"
Dynamic: license-file
